clenv/__init__.py
clenv/cli/__init__.py
clenv/cli/__main__.py
clenv/cli/config/__init__.py
clenv/cli/config/config_loader.py
clenv/cli/config/config_manager.py
clenv/cli/config/config_subcommand.py
clenv/cli/queue/__init__.py
clenv/cli/queue/queue_manager.py
clenv/cli/task/__init__.py
clenv/cli/task/task_subcommand.py
clenv/cli/user/__init__.py
clenv/cli/user/user_subcommand.py
clenv-0.0.8.dist-info/LICENSE
clenv-0.0.8.dist-info/METADATA
clenv-0.0.8.dist-info/WHEEL
clenv-0.0.8.dist-info/entry_points.txt
clenv-0.0.8.dist-info/top_level.txt
clenv-0.0.8.dist-info/RECORD
