Metadata-Version: 2.1
Name: clenv
Version: 0.0.8
Summary: ClearML config profile manager
Home-page: https://github.com/DavidSonoda/clenv
Author: Juewei Dong
Author-email: juewei.dong@brainco.tech
License: MIT
Classifier: Development Status :: 3 - Alpha
Classifier: Intended Audience :: Developers
Classifier: License :: OSI Approved :: MIT License
Classifier: Programming Language :: Python :: 3
Classifier: Programming Language :: Python :: 3.6
Classifier: Programming Language :: Python :: 3.7
Classifier: Programming Language :: Python :: 3.8
Classifier: Programming Language :: Python :: 3.9
Requires-Python: >=3.7
License-File: LICENSE
Requires-Dist: clearml (>=1.10.0)
Requires-Dist: click (>=8.1.0)
Requires-Dist: pyhocon (==0.3.35)
Requires-Dist: bcrypt (>=4.0.0)
Requires-Dist: GitPython (==3.1.31)
Requires-Dist: inquirerpy (==0.3.4)
